{
  "kind": "original",
  "electionId": "E-TCRCGS13B",
  "voter": "e5",
  "voterKind": "member",
  "choiceInternalNo": 1,
  "goa": 1,
  "reservation": null,
  "rationale": "0件で可(1)。e1 record 実測+PR #1401 独立レビュー(私)との突合: (1) FR-2b 引用誤り(tests/gen-coverage-registry.ts と誤記、実体は tests/unit/gen-coverage-registry.test.ts:855)は diary Interpretations 03:07:39Z に正誤固定済み — mechanism-cite-verify 違反実例+E-FSPRAS13 引用一意性追補の消費側実例で PM 回付が正位置。私の PR レビューでも registry pin :855-857 の実体を直読しており誤引用の非伝播(実装は正)を裏書きできる。(2) t257 一式は Mandated 落ちる実証+corpus-sweep+vacuity-guard(runtime 合成 MARKER)の機械的執行 — 私自身が注入→1 fail→byte-exact 復元→0 fail を独立再現済みで、執行の質も確認。(3) fixture 汚染3回目は既起票 #1389 のコメント追記で扱われ、修正は e4 intent(E-FSPRA1/2 裁定済み)進行中 — 二重対応なし。新規ノルム候補なしに同意。",
  "submittedAt": "2026-07-23T03:15:32Z"
}