{
  "electionId": "E-TCRBTS13",
  "kind": "s13-zero-confirm",
  "question": "intent 260723-t241-ci-residency(#1294)/ build-and-test の §13 学習選定: 採用0件の確認。conductor(e1)起案(verbatim 正本 = e1 ブランチの <record>/construction/build-and-test/s13-candidates.md — git show で実測可)。各自実測確認のうえ GoA 付きで投票。軽量様式可。",
  "choices": [
    {
      "internalNo": 1,
      "label": "0件で可"
    },
    {
      "internalNo": 2,
      "label": "異議 — 採用すべき候補がある(票コメントで特定)"
    }
  ],
  "voters": [
    "e4",
    "e5",
    "e6"
  ],
  "state": "collecting"
}